simple_zstd/__init__.py
simple_zstd-0.1.2.dist-info/METADATA
simple_zstd-0.1.2.dist-info/WHEEL
simple_zstd-0.1.2.dist-info/licenses/LICENSE
simple_zstd-0.1.2.dist-info/RECORD
