Metadata-Version: 2.4
Name: simple-zstd
Version: 0.1.2
Project-URL: Repository, https://github.com/chuanconggao/SimpleZstd/
Author-email: Chuancong Gao <chuanconggao@users.noreply.github.com>
License-Expression: MIT
License-File: LICENSE
Requires-Python: >=3.11
Requires-Dist: zstandard>=0.21.0
